[{"Year":2001,"Arrest":7150,"NonArrest":24233},{"Year":2002,"Arrest":7340,"NonArrest":24181},{"Year":2003,"Arrest":6909,"NonArrest":22568},{"Year":2004,"Arrest":7004,"NonArrest":21846},{"Year":2005,"Arrest":6631,"NonArrest":20435},{"Year":2006,"Arrest":6288,"NonArrest":19657},{"Year":2007,"Arrest":6550,"NonArrest":19764},{"Year":2008,"Arrest":5316,"NonArrest":20131},{"Year":2009,"Arrest":5700,"NonArrest":17161},{"Year":2010,"Arrest":5051,"NonArrest":16484},{"Year":2011,"Arrest":5185,"NonArrest":15225},{"Year":2012,"Arrest":4792,"NonArrest":15105},{"Year":2013,"Arrest":4460,"NonArrest":13511},{"Year":2014,"Arrest":4495,"NonArrest":12400},{"Year":2015,"Arrest":4038,"NonArrest":12989},{"Year":2016,"Arrest":null,"NonArrest":null}]